arcade_tdk/__init__.py
arcade_tdk/errors.py
arcade_tdk/py.typed
arcade_tdk/tool.py
arcade_tdk/utils.py
arcade_tdk/annotations/__init__.py
arcade_tdk/auth/__init__.py
arcade_tdk/error_adapters/__init__.py
arcade_tdk/error_adapters/base.py
arcade_tdk/error_adapters/utils.py
arcade_tdk/providers/__init__.py
arcade_tdk/providers/google/__init__.py
arcade_tdk/providers/google/error_adapter.py
arcade_tdk/providers/graphql/__init__.py
arcade_tdk/providers/graphql/error_adapter.py
arcade_tdk/providers/http/__init__.py
arcade_tdk/providers/http/error_adapter.py
arcade_tdk/providers/microsoft/__init__.py
arcade_tdk/providers/microsoft/error_adapter.py
arcade_tdk/providers/slack/__init__.py
arcade_tdk/providers/slack/error_adapter.py
arcade_tdk-3.4.0.dist-info/METADATA
arcade_tdk-3.4.0.dist-info/WHEEL
arcade_tdk-3.4.0.dist-info/RECORD
