Metadata-Version: 2.4
Name: arcade-tdk
Version: 3.4.0
Summary: Arcade TDK - Toolkit Development Kit for building Arcade tools
Author-email: Arcade <dev@arcade.dev>
License: MIT
Classifier: Development Status :: 5 - Production/Stable
Classifier: Intended Audience :: Developers
Classifier: License :: OSI Approved :: MIT License
Classifier: Programming Language :: Python :: 3
Classifier: Programming Language :: Python :: 3.10
Classifier: Programming Language :: Python :: 3.11
Classifier: Programming Language :: Python :: 3.12
Classifier: Programming Language :: Python :: 3.13
Requires-Python: >=3.10
Requires-Dist: arcade-core<5.0.0,>=4.1.0
Requires-Dist: pydantic>=2.7.0
Provides-Extra: dev
Requires-Dist: mypy>=1.5.1; extra == 'dev'
Requires-Dist: pre-commit>=3.4.0; extra == 'dev'
Requires-Dist: pytest-asyncio>=0.23.7; extra == 'dev'
Requires-Dist: pytest-cov>=4.0.0; extra == 'dev'
Requires-Dist: pytest>=8.1.2; extra == 'dev'
